autolink_references/__about__.py
autolink_references/__init__.py
autolink_references/main.py
autolink_references_mkdocs_plugin-0.2.2.dist-info/METADATA
autolink_references_mkdocs_plugin-0.2.2.dist-info/WHEEL
autolink_references_mkdocs_plugin-0.2.2.dist-info/entry_points.txt
autolink_references_mkdocs_plugin-0.2.2.dist-info/licenses/LICENSE
autolink_references_mkdocs_plugin-0.2.2.dist-info/RECORD
