Metadata-Version: 2.1
Name: autolink-references-mkdocs-plugin
Version: 0.2.2
Summary: This plugin allows to configure your own autolink references for non-GitHub URLs.
Project-URL: Documentation, https://github.com/theskumar/autolink-references-mkdocs-plugin/tree/main#readme
Project-URL: Source, https://github.com/theskumar/autolink-references-mkdocs-plugin
Project-URL: Tracker, https://github.com/theskumar/autolink-references-mkdocs-plugin/issues
Author-email: Saurabh Kumar <autolink-references-mkdocs-plugin@saurabh-kumar.com>
License-Expression: MIT
License-File: LICENSE
Keywords: autolinks,mkdocs,regex
Classifier: Development Status :: 4 - Beta
Classifier: Intended Audience :: Developers
Classifier: Intended Audience :: System Administrators
Classifier: License :: OSI Approved :: MIT License
Classifier: Operating System :: OS Independent
Classifier: Programming Language :: Python
Classifier: Programming Language :: Python :: 3.8
Classifier: Programming Language :: Python :: 3.9
Classifier: Programming Language :: Python :: 3.10
Classifier: Programming Language :: Python :: 3.11
Classifier: Programming Language :: Python :: 3.12
Classifier: Topic :: Utilities
Requires-Python: >=3.8
Requires-Dist: mkdocs
